pytauri_wheel/__init__.py
pytauri_wheel/ext_mod.cpython-313-aarch64-linux-gnu.so
pytauri_wheel/lib.py
pytauri_wheel/py.typed
pytauri_wheel-0.8.0.dist-info/METADATA
pytauri_wheel-0.8.0.dist-info/WHEEL
pytauri_wheel-0.8.0.dist-info/entry_points.txt
pytauri_wheel-0.8.0.dist-info/top_level.txt
pytauri_wheel-0.8.0.dist-info/RECORD
