Metadata-Version: 2.4
Name: pytauri-wheel
Version: 0.8.0
Summary: Precompiled wheels for pytauri
Author-email: Sean Wang <126865849+WSH032@users.noreply.github.com>
License-Expression: Apache-2.0
Project-URL: documentation, https://pytauri.github.io/pytauri/
Project-URL: source, https://github.com/pytauri/pytauri
Requires-Python: >=3.9
Requires-Dist: typing-extensions>=4.14
Requires-Dist: pytauri==0.8.*
